nios_2.v
module nios_2 (
input clk,
input rst,
input enable,  // Enables Nios2
input  [31:0] inst_fetch,
output wire [7:0] prog_count_o,
output wire        data_mem_wr_o,    // Data memory Write Operation
output wire        data_mem_rd_o,    // Data memory Read Operation
output wire [31:0] data_mem_addr_o,  // Data memory Address
output wire [31:0] data_mem_wdata_o,  // Write Data
input       [31:0] data_mem_rdata_i   // Data Memory Read Data
);

wire  [7:0] prog_count_c;
wire  [5:0] opcode_c;  // Opcode extraction from memory Fetch
wire [10:0] opcode_ext_c;  // Opcode Extension for R-type
wire [31:0] immi_val_c;  // Sign extended immidiate value
wire  [4:0] rega_addr_c; // Address of Register A
wire  [4:0] regb_addr_c; // Address of Register B
wire  [4:0] regc_addr_c; // Address of Register C
reg   [4:0] rega_addr; // Address of Register A for execute Stage
reg   [4:0] regb_addr; // Address of Register B for execute Stage
reg   [4:0] regc_addr; // Address of Register C for execute Stage
reg   [4:0] rega_addr_mem; //Address of Register A for memory Stage
reg   [4:0] regb_addr_mem; //Address of Register B for memory Stage
reg   [4:0] regc_addr_mem; //Address of Register C for memory Stage
reg   [4:0] rega_addr_wb; //Address of Register A for Write back Stage
reg   [4:0] regb_addr_wb; //Address of Register B for Write back Stage
reg   [4:0] regc_addr_wb; //Address of Register C for Write back Stage
reg         forwarding;   // Indicates Forwarding for data hazard
wire [31:0] twos_comp;  // Two's compliment for addition
wire [31:0] alu_op_c;  // ALU Operation Output
wire  [1:0] alu_opr_c; // ALU Operation 00 -- No Operation
                       //               01 -- Addition
                       //               10 -- Substraction
                       //               11 -- Multiplication
wire        mem_op_c;       // Data Memory Operation

wire        wb_exec;      // Write Back Stage Need Execution
wire [31:0] wb_data;      // Write Back State Data
wire  [4:0] wb_reg_addr;  // Write Back Stage Address of register
wire        cmp_op_c;     // Comparision Operation
wire        branch_taken; // Indicates Branch is taken
wire        equ_chk_c;    // Equality Check Operation
wire        non_equ_c;    // Non Equality Check Operation
wire        uncnd_jmp_inst_r_typ; // Unconditional Jump Instruction R-type
wire        uncnd_jmp_inst_j_typ; // Unconditional Jump Instruction J-type
// wire        wr_prog_cnt_c;        // Write back programme counter to Register 31

reg [31:0] reg_mem [31:0];
reg  [7:0] prog_count;
reg  [7:0] prog_count_de; // Program Count in Decode Stage
reg  [7:0] prog_count_ex; // Program Count in Execution Stage
reg  [5:0] opcode_ex;   // Opcode for Execution Stage
reg  [5:0] opcode_mem;  // Opcode for Memory Stage
reg [10:0] opcode_ext_ex;  // Opcode Extension for R-type execution Stage
reg [10:0] opcode_ext_mem;  // Opcode Extension for R-type Memory Stage
reg [31:0] immi_val;    // Immidiate value for Execution stage
reg [31:0] regA;        // Register to be used in Execution Stage
reg [31:0] regB;        // Register to be used in Execution Stage
reg [31:0] regC;        // Register to be used in Execution Stage
reg [31:0] regA_mem;    // Register to be used in Memory Stage
reg [31:0] regB_mem;    // Register to be used in Memory Stage
reg [31:0] regC_mem;    // Register to be used in Memory Stage
reg [31:0] alu_op;      // ALU Output Registed version
reg [31:0] alu_op_wb;   // ALU Output Registed version for use in Write Back Stage
reg        i_type;      // I-Type instruction flag is used for Execution stage
reg        j_type;      // J-Type instruction flag is used for Execution stage
reg        r_type;      // R-Type instruction flag is used for Execution stage
reg        i_type_mem; // I-Type instruction flag is used for Memory stage
reg        j_type_mem; // J-Type instruction flag is used for Memory stage
reg        r_type_mem; // R-Type instruction flag is used for Memory stage
reg        i_type_wb; // I-Type instruction flag is used for Write Back stage
reg        j_type_wb; // J-Type instruction flag is used for Write Back stage
reg        r_type_wb; // R-Type instruction flag is used for Write Back stage
reg        data_mem_rd_d;
//-------------------------------------------
// Instruction Fetch
//-------------------------------------------

assign prog_count_o = prog_count;

assign prog_count_c={8{enable & !branch_taken & !uncnd_jmp_inst_r_typ & !uncnd_jmp_inst_j_typ}} & (prog_count + 8'h04)  |
                    {8{enable & !branch_taken &  uncnd_jmp_inst_r_typ}} & (regA)                |
                    {8{enable & !branch_taken &  uncnd_jmp_inst_j_typ}} & (immi_val)            |
                    {8{enable &  branch_taken &  cmp_op_c}} & (immi_val)                        |
                    {8{enable &  branch_taken }} & (alu_op_c)            | 
                    {8{~enable}} & prog_count;


assign opcode_c = inst_fetch[5:0];

assign i_type_c = ( (opcode_c == 6'h04) |
                    (opcode_c == 6'h15) |
                    (opcode_c == 6'h16) |
                    (opcode_c == 6'h17) |
                    (opcode_c == 6'h1E) |
                    (opcode_c == 6'h26));
 
assign j_type_c = (opcode_c == 6'h06) |
                  (opcode_c == 6'h00);

assign r_type_c = ( (opcode_c == 6'h3A) |
                    (opcode_c == 6'h31));

//-------------------------------------------
// Instruction Decode/ Register Fetch
//-------------------------------------------
assign rega_addr_c = {5{(i_type_c | r_type_c)}} & inst_fetch[31:27];

assign regb_addr_c = {5{(i_type_c | r_type_c)}} & inst_fetch[26:22];

assign regc_addr_c = {5{r_type_c}} & inst_fetch[21:17] |
                     {5{(opcode_c == 6'h00)}} & 6'h1F;  // Add code for opcode extension

assign immi_val_c = {32{i_type_c}} & {{16{inst_fetch[21]}}, inst_fetch[21:6]} |
                    {32{j_type_c}} & {5'h00,inst_fetch[31:6]};

assign opcode_ext_c = {11{r_type_c}} & inst_fetch[16:6];




//-------------------------------------------
// Execution Stage
//-------------------------------------------

assign cmp_op_c =  (opcode_ex == 6'h16);

assign equ_chk_c =  (opcode_ex == 6'h26);  // Equality Check

assign non_equ_c = (opcode_ex == 6'h1E);  // Non Equality Check

assign alu_opr_c = {2{((opcode_ex == 6'h31) | 
                       (opcode_ex == 6'h04 & !immi_val[31]) | 
                       (opcode_ex == 6'h15) | 
                       (opcode_ex == 6'h1E) | 
                       (opcode_ex == 6'h26) | 
                       (opcode_ex == 6'h00) | 
                       (opcode_ex == 6'h17))}} & 2'b01 |
                   {2{(opcode_ex == 6'h04 & immi_val[31])}} & 2'b10 | 
                   {2{((opcode_ex == 6'h3A) & (opcode_ext_ex == 6'h27))}} & 2'b11;

assign branch_taken = ((cmp_op_c)  & (regB > regA))  |
                      ((non_equ_c) & (regB != regA)) |
                      ((equ_chk_c) & (regB == regA));

assign uncnd_jmp_inst_r_typ = ((opcode_ex == 6'h3A) & (opcode_ext_ex == 6'h1D));  // Unconditional Jump Instruction R-type
assign uncnd_jmp_inst_j_typ = (opcode_ex == 6'h00);  // Unconditional Jump Instruction J-type
// assign wr_prog_cnt_c = (opcode_ex == 6'h00);         // Write back programme counter to Register 31
assign twos_comp = ((~immi_val) + 1'b1);             // Two's compliment for addition

assign alu_op_c = {32{(alu_opr_c == 2'b01) & i_type & !branch_taken}} & (regA + immi_val) |
                  {32{(alu_opr_c == 2'b01) & i_type &  branch_taken}} & (prog_count_ex + immi_val) |
                  {32{(alu_opr_c == 2'b01) & uncnd_jmp_inst_j_typ}} & (prog_count_ex + 32'h04) |
                  {32{(alu_opr_c == 2'b01) & r_type}} & (regA + regB)     |
                  {32{(alu_opr_c == 2'b10) & i_type}} & (regA - twos_comp)  |
                  {32{(alu_opr_c == 2'b11) & i_type}} & (regA * immi_val) |
                  {32{(alu_opr_c == 2'b11) & r_type}} & (regA * regB);

//-------------------------------------------
// Memory Stage
//-------------------------------------------

assign mem_op_c         = (data_mem_rd_o | data_mem_wr_o);
assign data_mem_rd_o    = (opcode_mem == 6'h17);
assign data_mem_wr_o    = (opcode_mem == 6'h15);
assign data_mem_addr_o  = {32{mem_op_c}} & alu_op;
assign data_mem_wdata_o = {32{mem_op_c}} & regB_mem;

assign i_type_wb_c = (i_type_mem & (opcode_mem == 6'h04));
assign j_type_wb_c = (j_type_mem & (opcode_mem == 6'h00));


//-------------------------------------------
// Write Back Stage
//-------------------------------------------

assign wb_exec     =  data_mem_rd_d | r_type_wb | i_type_wb | j_type_wb;
assign wb_data     = {32{data_mem_rd_d}} & data_mem_rdata_i |
                     {32{r_type_wb | i_type_wb | j_type_wb}}     & alu_op_wb;
assign wb_reg_addr = {5{data_mem_rd_d | i_type_wb}} & regb_addr_wb |
                     {5{r_type_wb | j_type_wb}}     & regc_addr_wb;


always @ (posedge clk or negedge rst)
begin
  if(!rst) 
  begin
    reg_mem[0]    <= #1 'h00;
    reg_mem[1]    <= #1 'h00;
    reg_mem[2]    <= #1 'h00;
    reg_mem[3]    <= #1 'h00;
    reg_mem[4]    <= #1 'h04;
    reg_mem[5]    <= #1 'h00;
    reg_mem[6]    <= #1 'h00;
    reg_mem[7]    <= #1 'h00;
    reg_mem[8]    <= #1 'h00;
    reg_mem[9]    <= #1 'h00;
    reg_mem[8'h1D]<= #1 'h0000FFFF;
    reg_mem[8'h1E]<= #1 'h00;
    reg_mem[8'h1F]<= #1 'hA0;
    prog_count    <= #1 8'h00;
    prog_count_de <= #1 8'h00;
    prog_count_ex <= #1 8'h00;
    immi_val      <= #1 32'h00;
    opcode_ext_ex <= #1 10'h00;
    opcode_ext_mem<= #1 10'h00;
    regA          <= #1 32'h00;
    regB          <= #1 32'h00;
    regC          <= #1 32'h00;
    rega_addr     <= #1 'h00; 
    regb_addr     <= #1 'h00; 
    regc_addr     <= #1 'h00; 
    rega_addr_mem <= #1 'h00; 
    regb_addr_mem <= #1 'h00; 
    regc_addr_mem <= #1 'h00; 
    rega_addr_wb  <= #1 'h00; 
    regb_addr_wb  <= #1 'h00; 
    regc_addr_wb  <= #1 'h00; 
    regA_mem      <= #1 32'h00;
    regB_mem      <= #1 32'h00;
    regC_mem      <= #1 32'h00;
    opcode_ex     <= #1 'h00;
    opcode_mem    <= #1 'h00;
    i_type        <= #1 'b0;
    j_type        <= #1 'b0;
    r_type        <= #1 'b0;
    i_type_mem    <= #1 'b0;
    j_type_mem    <= #1 'b0;
    r_type_mem    <= #1 'b0;
    i_type_wb     <= #1 'b0;
    j_type_wb     <= #1 'b0;
    r_type_wb     <= #1 'b0;
    alu_op        <= #1 32'h0000;
    alu_op_wb     <= #1 32'h0000;
    data_mem_rd_d <= #1 'h0;
    forwarding    <= #1 1'b0;
  end
  else
  begin
    if((rega_addr_c == regb_addr) & (rega_addr_c != 5'b0) & (opcode_ex != 5'h15)) begin
     regA          <= #1 alu_op_c;
     forwarding    <= #1 1'b1;
    end 
    else if( (rega_addr_c == regb_addr_mem) & (rega_addr_c != 5'b0)) begin
     regA          <= #1 alu_op;
     forwarding    <= #1 1'b1;
    end
    else begin
     regA          <= #1 reg_mem[rega_addr_c];
     forwarding    <= #1 1'b0;
    end
     regB           <= #1 reg_mem[regb_addr_c];
     regC           <= #1 reg_mem[regc_addr_c];
     regA_mem       <= #1 regA;
     regB_mem       <= #1 regB;
     regC_mem       <= #1 regC;
     rega_addr      <= #1 rega_addr_c;
     regb_addr      <= #1 regb_addr_c;
     regc_addr      <= #1 regc_addr_c;
     rega_addr_mem  <= #1 rega_addr;
     regb_addr_mem  <= #1 regb_addr;
     regc_addr_mem  <= #1 regc_addr;
     rega_addr_wb   <= #1 rega_addr_mem;
     regb_addr_wb   <= #1 regb_addr_mem;
     regc_addr_wb   <= #1 regc_addr_mem;
     prog_count     <= #1 prog_count_c;
     prog_count_de  <= #1 prog_count;
     prog_count_ex  <= #1 prog_count_de;
     opcode_ext_ex  <= #1 opcode_ext_c;
     opcode_ext_mem <= #1 opcode_ext_ex;
     immi_val       <= #1 immi_val_c;
     opcode_ex      <= #1 opcode_c;
     opcode_mem     <= #1 opcode_ex;
     i_type         <= #1 i_type_c;
     j_type         <= #1 j_type_c;
     r_type         <= #1 r_type_c;
     i_type_mem     <= #1 i_type;
     j_type_mem     <= #1 j_type;
     r_type_mem     <= #1 r_type;
     i_type_wb      <= #1 i_type_wb_c;
     j_type_wb      <= #1 j_type_wb_c;
     r_type_wb      <= #1 r_type_mem;
     alu_op         <= #1 alu_op_c;
     alu_op_wb      <= #1 alu_op;
     data_mem_rd_d  <= #1 data_mem_rd_o;
     if (wb_exec) begin
//      $display("Write @ Reg[%d] = %d ",wb_reg_addr,wb_data);
      reg_mem[wb_reg_addr] <= #1 wb_data;
     end
  end
end

endmodule

tb_nios_2_dot_product.v
module tb_nios_2;

reg         clk,rst,enable;
reg  [31:0] inst_mem_o;
reg  [31:0] inst_mem [255:0];
reg  [31:0] data_mem_rdata;
wire [31:0] data_mem_addr;  // Data memory Address
wire [31:0] data_mem_wdata;  // Write Data
wire        data_mem_wr;    // Data memory Write Operation
wire        data_mem_rd;    // Data memory Read Operation
wire  [7:0]prog_count;
reg  [31:0] data_mem[0:65536];

always #5 clk = ~clk;

always @ (posedge clk)
begin
  if (enable)
  begin
    inst_mem_o <= #1 inst_mem[prog_count];
  end
  else
  begin
    inst_mem_o <= #1 inst_mem_o;
  end
end

always @ (posedge clk)
begin
  if (data_mem_wr) begin
    data_mem[data_mem_addr] <= #1 data_mem_wdata;
  $display("Memory Write Occured with addr:%h = %h",data_mem_addr,data_mem_wdata);
  end
  if (data_mem_rd) begin   
  data_mem_rdata <= #1 data_mem[data_mem_addr];
  $display("Memory read Occured with addr:%h = %h",data_mem_addr,data_mem[data_mem_addr]);
  end
end

initial
begin
 $dumpfile("nios2.vcd");
 $dumpvars("0");
end


initial
begin
clk = 0;
rst = 1;
enable = 0;
data_mem_rdata = 32'h0000;
data_mem[16'h10] = 32'd0005; // Load it value minus one
data_mem[16'h20] = 32'd0005;
data_mem[16'h24] = 32'd0003;
data_mem[16'h28] = 32'd0006;
data_mem[16'h2C] = 32'd0019;
data_mem[16'h30] = 32'd0008;
data_mem[16'h34] = 32'd0012;
data_mem[16'h40] = 32'd0002;
data_mem[16'h44] = 32'd0014;
data_mem[16'h48] = 32'd0003;
data_mem[16'h4C] = 32'd0002;
data_mem[16'h50] = 32'd0005;
data_mem[16'h54] = 32'd0036;
data_mem[16'h82] = 32'h0009;
inst_mem[8'h0] = 32'b00000_00010_0000_0000_0010_0000_000100;  // addi $2,$0,20 ( A_VECTOR )
inst_mem[8'h4] = 32'b00000_00011_0000_0000_0100_0000_000100;  // addi $3,$0,40 ( B_VECTOR )
inst_mem[8'h8] = 32'b00000_00100_0000_0000_0001_0000_000100;  // addi $4,$0,10 ( Number )
inst_mem[8'hC] = 32'h00000001;  // Stall - 2 Due to data dependenct
inst_mem[8'h10] = 32'h00000001;  // Stall - 3 Due to data dependenct
inst_mem[8'h14] = 32'h00000001;  // Stall - 3 Due to data dependenct
inst_mem[8'h18] = 32'b00100_00100_0000_0000_0000_0000_010111;  // ldw $4,0($4)
inst_mem[8'h1C] = 32'b00000_00000_0010_1000_0011_0001_110001;  // add $5,$0,$0
inst_mem[8'h20] = 32'b00010_00110_0000_0000_0000_0000_010111;   // LOOP: LDW R6, 0(R2); 
inst_mem[8'h24] = 32'b00011_00111_0000_0000_0000_0000_010111;   //       LDW R7, 0(R3);  
inst_mem[8'h28] = 32'h00000001;  // Stall
inst_mem[8'h2C] = 32'h00000001;  // Stall - 1 Due to data dependenct
inst_mem[8'h30] = 32'h00000001;  // Stall - 2 Due to data dependenct
inst_mem[8'h34] = 32'h00000001;  // Stall - 3 Due to data dependenct
inst_mem[8'h38] = 32'b00110_00111_0100_0000_0010_0111_111010;   //       MUL R8, R6, R7
inst_mem[8'h3C] = 32'h00000001;  // Stall
inst_mem[8'h40] = 32'h00000001;  // Stall - 2 Due to data dependenct
inst_mem[8'h44] = 32'h00000001;  // Stall - 3 Due to data dependenct
inst_mem[8'h48] = 32'h00000001;  // Stall - 1 Due to data dependenct // Unneccesary stall can remove
inst_mem[8'h4C] = 32'b00101_01000_0010_1000_0011_0001_110001;   //       ADD R5, R5, R8
inst_mem[8'h50] = 32'b00010_00010_0000_0000_0000_0100_000100;   //       ADDI R2, R2, 4
inst_mem[8'h54] = 32'b00011_00011_0000_0000_0000_0100_000100;   //       ADDI R3, R3, 4
inst_mem[8'h58] = 32'b00100_00100_1111_1111_1111_1111_000100;   //       ADDI R4, R4, -1
inst_mem[8'h5C] = 32'b00000_00100_0000_0000_0010_0000_010110;   //       BLT R0, R4, LOOP
inst_mem[8'h60] = 32'h00000001;  // Stall - 1 Due to Control Hazard
inst_mem[8'h64] = 32'h00000001;  // Stall - 2 Due to Control Hazard
inst_mem[8'h68] = 32'h00000001;  // Stall - 2 Due to Control Hazard
inst_mem[8'h6C] = 32'b00000_00101_0000_0000_0000_0000_010101;   //       STW R5, DOT_PRODUCT(R0)
inst_mem[8'h70] = 32'h00000001;  // Stall - 1 Due to Control Hazard
//inst_mem[8'h74] = 32'h00000001;  // Stall - 2 Due to Control Hazard
//inst_mem[8'h78] = 32'h00000001;  // Stall - 2 Due to Control Hazard
//inst_mem[8'h7C] = 32'h208409FA;  // mult 2,2,4
//inst_mem[8'h80] = 32'hEFC00117;  // ldw 31,4(29)
//inst_mem[8'h84] = 32'hEF800217;  // ldw 30,8(29)
//inst_mem[8'h88] = 32'hEF400304;  // addi 29,29,12 
//inst_mem[8'h8C] = 32'h00000001;  // Stall - 1 Due to Control Hazard
//inst_mem[8'h90] = 32'h00000001;  // Stall - 2 Due to Control Hazard
//inst_mem[8'h94] = 32'h00000001;  // Stall - 2 Due to Control Hazard
//inst_mem[8'h98] = 32'hF800077A;  // Jump Instruction call subroutine jr $31
//inst_mem[8'h9C] = 32'h00000001;  // Stall - 2 Due to Control Hazard
//inst_mem[8'hA0] = 32'h00000001;  // Stall - 2 Due to Control Hazard
//inst_mem[8'h14] = 32'h21400144;
// inst_mem[8'h18] = 32'h00000200;
// orig inst_mem[0] = 32'b00000001010000000001100100010101;
// orig inst_mem[1] = 32'b00101010000010111000100000110001;
// orig inst_mem[5] = 32'b00101010000010111000100000110001;
// orig inst_mem[6] = 32'b00010001100000000010000000010111;
// orig inst_mem[3] = 32'b00000000100000000000000000110100;
// orig inst_mem[4] = 32'b00010000100000000000010100010100;
// orig inst_mem[2] = 32'b00000001010000000000000000010110;
//inst_mem[5] = 32'b00010000100000000000000100000100;
//inst_mem[6] = 32'b00000001000000000000100000010110;
// orig inst_mem[7] = 32'b00110001110100010011100000111010;
// orig inst_mem[8] = 32'h20000126;
inst_mem[9] = 32'h00000001;
inst_mem_o = 32'h00000001;
#5 rst = 0;
#20 rst = 1;
#5 enable = 1;
#2350 enable = 0;

#200 $finish;
end

nios_2 nios_2_inst ( .clk(clk),
                     .rst(rst),
                     .enable(enable),
                     .inst_fetch(inst_mem_o),
                     .prog_count_o(prog_count),
                     .data_mem_wr_o(data_mem_wr),    // Data memory Write Operation
                     .data_mem_rd_o(data_mem_rd),    // Data memory Read Operation
                     .data_mem_addr_o(data_mem_addr),  // Data memory Address
                     .data_mem_wdata_o(data_mem_wdata),  // Write Data
                     .data_mem_rdata_i(data_mem_rdata)
);


endmodule

nios2.vcd
$date
	Sun May 15 22:31:07 2016
$end

$version
	Synopsys VCS version I-2014.03-2
$end

$timescale
	1s
$end

$comment Csum: 1 2d447f28439ae882 $end


$scope module tb_nios_2 $end
$var reg 1 ! clk $end
$var reg 1 " rst $end
$var reg 1 # enable $end
$var reg 32 $ inst_mem_o [31:0] $end
$var reg 32 % data_mem_rdata [31:0] $end
$var wire 32 & data_mem_addr [31:0] $end
$var wire 32 ' data_mem_wdata [31:0] $end
$var wire 1 ( data_mem_wr $end
$var wire 1 ) data_mem_rd $end
$var wire 8 * prog_count [7:0] $end

$scope module nios_2_inst $end
$var wire 1 ! clk $end
$var wire 1 " rst $end
$var wire 1 # enable $end
$var wire 32 $ inst_fetch [31:0] $end
$var wire 8 * prog_count_o [7:0] $end
$var wire 1 ( data_mem_wr_o $end
$var wire 1 ) data_mem_rd_o $end
$var wire 32 & data_mem_addr_o [31:0] $end
$var wire 32 ' data_mem_wdata_o [31:0] $end
$var wire 32 % data_mem_rdata_i [31:0] $end
$var wire 8 + prog_count_c [7:0] $end
$var wire 6 , opcode_c [5:0] $end
$var wire 11 - opcode_ext_c [10:0] $end
$var wire 32 . immi_val_c [31:0] $end
$var wire 5 / rega_addr_c [4:0] $end
$var wire 5 0 regb_addr_c [4:0] $end
$var wire 5 1 regc_addr_c [4:0] $end
$var reg 5 2 rega_addr [4:0] $end
$var reg 5 3 regb_addr [4:0] $end
$var reg 5 4 regc_addr [4:0] $end
$var reg 5 5 rega_addr_mem [4:0] $end
$var reg 5 6 regb_addr_mem [4:0] $end
$var reg 5 7 regc_addr_mem [4:0] $end
$var reg 5 8 rega_addr_wb [4:0] $end
$var reg 5 9 regb_addr_wb [4:0] $end
$var reg 5 : regc_addr_wb [4:0] $end
$var reg 1 ; forwarding $end
$var wire 32 < twos_comp [31:0] $end
$var wire 32 = alu_op_c [31:0] $end
$var wire 2 > alu_opr_c [1:0] $end
$var wire 1 ? mem_op_c $end
$var wire 1 @ wb_exec $end
$var wire 32 A wb_data [31:0] $end
$var wire 5 B wb_reg_addr [4:0] $end
$var wire 1 C cmp_op_c $end
$var wire 1 D branch_taken $end
$var wire 1 E equ_chk_c $end
$var wire 1 F non_equ_c $end
$var wire 1 G uncnd_jmp_inst_r_typ $end
$var wire 1 H uncnd_jmp_inst_j_typ $end
$var reg 8 I prog_count [7:0] $end
$var reg 8 J prog_count_de [7:0] $end
$var reg 8 K prog_count_ex [7:0] $end
$var reg 6 L opcode_ex [5:0] $end
$var reg 6 M opcode_mem [5:0] $end
$var reg 11 N opcode_ext_ex [10:0] $end
$var reg 11 O opcode_ext_mem [10:0] $end
$var reg 32 P immi_val [31:0] $end
$var reg 32 Q regA [31:0] $end
$var reg 32 R regB [31:0] $end
$var reg 32 S regC [31:0] $end
$var reg 32 T regA_mem [31:0] $end
$var reg 32 U regB_mem [31:0] $end
$var reg 32 V regC_mem [31:0] $end
$var reg 32 W alu_op [31:0] $end
$var reg 32 X alu_op_wb [31:0] $end
$var reg 1 Y i_type $end
$var reg 1 Z j_type $end
$var reg 1 [ r_type $end
$var reg 1 \ i_type_mem $end
$var reg 1 ] j_type_mem $end
$var reg 1 ^ r_type_mem $end
$var reg 1 _ i_type_wb $end
$var reg 1 ` j_type_wb $end
$var reg 1 a r_type_wb $end
$var reg 1 b data_mem_rd_d $end
$var wire 1 c i_type_c $end
$var wire 1 d j_type_c $end
$var wire 1 e r_type_c $end
$var wire 1 f i_type_wb_c $end
$var wire 1 g j_type_wb_c $end
$upscope $end

$upscope $end

$enddefinitions $end

#0
$dumpvars
xD
0!
xC
x)
xb
x(
0#
xE
x;
xY
0c
x\
x_
xf
xZ
0d
x]
x`
xg
x?
xF
x[
0e
x^
xa
1"
xH
xG
x@
bxxxxxxxxxxxxxxxxxxxxxxxxxxxxxxxx W
bxxxxxxxxxxxxxxxxxxxxxxxxxxxxxxxx =
bxxxxxxxxxxxxxxxxxxxxxxxxxxxxxxxx X
bxx >
bxxxxxxxxxxxxxxxxxxxxxxxxxxxxxxxx &
b00000000000000000000000000000000 %
bxxxxxxxxxxxxxxxxxxxxxxxxxxxxxxxx '
bxxxxxxxxxxxxxxxxxxxxxxxxxxxxxxxx P
b00000000000000000000000000000000 .
b00000000000000000000000000000001 $
bxxxxxxxx I
b000001 ,
bxxxxxx L
b00000000000 -
bxxxxxxxxxxx N
bxxxxxxxxxxx O
bxxxxxx M
bxxxxxxxx *
bxxxxxxxx +
bxxxxxxxx J
bxxxxxxxx K
bxxxxxxxxxxxxxxxxxxxxxxxxxxxxxxxx Q
bxxxxxxxxxxxxxxxxxxxxxxxxxxxxxxxx T
bxxxxxxxxxxxxxxxxxxxxxxxxxxxxxxxx R
bxxxxxxxxxxxxxxxxxxxxxxxxxxxxxxxx U
bxxxxxxxxxxxxxxxxxxxxxxxxxxxxxxxx S
bxxxxxxxxxxxxxxxxxxxxxxxxxxxxxxxx V
bxxxxx 2
b00000 /
bxxxxx 5
bxxxxx 8
bxxxxx 3
b00000 0
bxxxxx 6
bxxxxx 9
bxxxxx 4
b00000 1
bxxxxx 7
bxxxxx :
bxxxxxxxxxxxxxxxxxxxxxxxxxxxxxxxx <
bxxxxxxxxxxxxxxxxxxxxxxxxxxxxxxxx A
bxxxxx B
$end
#5
1!
0"
#6
b00000000 I
b00000000 *
b00000000 J
b00000000 K
b00000000000000000000000000000000 P
b00000000000000000000000000000000 <
b00000000000 N
0G
b00000000000 O
b00000000000000000000000000000000 Q
b00000000000000000000000000000000 R
b00000000000000000000000000000000 S
b00000 2
b00000 3
b00000 4
b00000 5
b00000 6
b00000 7
b00000 8
b00000 9
b00000 :
b00000000000000000000000000000000 T
b00000000000000000000000000000000 U
b00000000000000000000000000000000 V
b000000 L
0C
0E
0F
1H
b000000 M
0?
0)
0(
0f
0g
0Y
0Z
0[
0\
0]
0^
0_
0`
0a
b00000000000000000000000000000000 W
b00000000000000000000000000000000 X
0b
0;
b00000000 +
b01 >
b00000000000000000000000000000100 =
b00000 B
b00000000000000000000000000000000 '
0D
b00000000000000000000000000000000 &
b00000000000000000000000000000000 A
0@
#10
0!
#15
1!
#20
0!
#25
1"
1!
#26
b000001 L
0H
b00000000000000000000000000000100 W
b00 >
b00000000000000000000000000000000 =
#30
1#
0!
b00000100 +
#35
1!
#36
b00000000010000000000000001000100 $
b000100 ,
b00000100 I
b00000100 *
b000001 M
b00000000000000000000000000000000 W
b00000000000000000000000000000100 X
1c
b00001000 +
b00000000000000000000000000000001 .
b00001 0
#40
0!
#45
1!
#46
b00000001000000000000100000100110 $
b100110 ,
b00001 3
b00001000 I
b00001000 *
b00000100 J
b00000000000000000000000000000001 P
b11111111111111111111111111111111 <
b000100 L
1Y
b00000000000000000000000000000000 X
b00000000000000000000000000100000 .
b00100 0
b00001100 +
b01 >
b00000000000000000000000000000001 =
#50
0!
#55
1!
#56
b00000000000000000000000000000001 $
b000001 ,
b00000000000000000000000000000100 R
b00100 3
b00001 6
b00001100 I
b00001100 *
b00001000 J
b00000100 K
b00000000000000000000000000100000 P
b11111111111111111111111111100000 <
b100110 L
1E
b000100 M
1f
1\
b00000000000000000000000000000001 W
0c
b00000000000000000000000000000000 .
b00000 0
b00010000 +
b00000000000000000000000000100000 =
#60
0!
#65
1!
#66
b00001001000000000000100100011110 $
b011110 ,
b00000000000000000000000000000000 R
b00000000000000000000000000000100 U
b00000 3
b00100 6
b00001 9
b00010000 I
b00010000 *
b00001100 J
b00001000 K
b00000000000000000000000000000000 P
b00000000000000000000000000000000 <
b000001 L
0E
b100110 M
0f
0Y
1_
b00000000000000000000000000100000 W
b00000000000000000000000000000001 X
1c
0D
b00010100 +
b00000000000000000000000000000000 =
b00 >
b00001 B
1@
b00000000000000000000000000000001 A
b00000000000000000000000000100100 .
b00001 /
b00100 0
#70
0!
#75
1!
#76
b00000000000000000000000000000001 $
b000001 ,
b00000000000000000000000000000100 R
b00000000000000000000000000000000 U
b00001 2
b00100 3
b00000 6
b00100 9
b00010100 I
b00010100 *
b00010000 J
b00001100 K
b00000000000000000000000000100100 P
b11111111111111111111111111011100 <
b011110 L
1F
b000001 M
1Y
0\
0_
b00000000000000000000000000000000 W
b00000000000000000000000000100000 X
0c
b00000000000000000000000000000000 .
b00000 /
b00000 0
b00000 B
b00011000 +
b01 >
1D
b00000000000000000000000000000000 A
0@
b00000000000000000000000000110000 =
b00110000 +
#80
0!
#85
1!
#86
b00000000000000000000000000000000 R
b00000000000000000000000000000100 U
b00000 2
b00000 3
b00001 5
b00100 6
b00000 9
b00110000 I
b00110000 *
b00010100 J
b00010000 K
b00000000000000000000000000000000 P
b00000000000000000000000000000000 <
b000001 L
0F
b011110 M
0Y
1\
b00000000000000000000000000110000 W
b00000000000000000000000000000000 X
0D
b00110100 +
b00000000000000000000000000000000 =
b00 >
#90
0!
#95
1!
#96
b00000000000000000000000000000000 U
b00000 5
b00000 6
b00001 8
b00100 9
b00110100 I
b00110100 *
b00110000 J
b00010100 K
b000001 M
0\
b00000000000000000000000000000000 W
b00000000000000000000000000110000 X
b00111000 +
#100
0!
#105
1!
#106
b00000 8
b00000 9
b00111000 I
b00111000 *
b00110100 J
b00110000 K
b00000000000000000000000000000000 X
b00111100 +
#110
0!
#115
1!
#116
b11101111011111111111110100000100 $
b000100 ,
b00111100 I
b00111100 *
b00111000 J
b00110100 K
1c
b01000000 +
b11111111111111111111111111110100 .
b11101 /
b11101 0
#120
0!
#125
1!
#126
b11101111100000000000001000010101 $
b010101 ,
b00000000000000001111111111111111 Q
b00000000000000001111111111111111 R
b11101 2
b11101 3
b01000000 I
b01000000 *
b00111100 J
b00111000 K
b11111111111111111111111111110100 P
b00000000000000000000000000001100 <
b000100 L
1Y
b00000000000000000000000000001000 .
b11110 0
b01000100 +
b10 >
b00000000000000001111111111110011 =
#130
0!
#135
1!
#136
b11101111110000000000000100010101 $
b00000000000000001111111111110011 Q
1;
b00000000000000000000000000000000 R
b00000000000000001111111111111111 T
b00000000000000001111111111111111 U
b11110 3
b11101 5
b11101 6
b01000100 I
b01000100 *
b01000000 J
b00111100 K
b00000000000000000000000000001000 P
b11111111111111111111111111111000 <
b010101 L
b000100 M
1f
1\
b00000000000000001111111111110011 W
b00000000000000000000000000000100 .
b11111 0
b00000000000000001111111111111011 =
b01001000 +
b01 >
#140
0!
#145
1!
#146
b00000000000000000000000000000001 $
b000001 ,
b00000000000000000000000010100000 R
b00000000000000001111111111110011 T
b00000000000000000000000000000000 U
b11111 3
b11110 6
b11101 8
b11101 9
b01001000 I
b01001000 *
b01000100 J
b01000000 K
b00000000000000000000000000000100 P
b11111111111111111111111111111100 <
b010101 M
1?
1(
0f
1_
b00000000000000001111111111111011 W
b00000000000000001111111111110011 X
0c
b00000000000000000000000000000000 .
b00000 /
b00000 0
b01001100 +
b00000000000000001111111111110111 =
b00000000000000001111111111111011 &
b11101 B
1@
b00000000000000001111111111110011 A
#150
0!
#155
1!
